runstats/__init__.py
runstats/_core.py
runstats/core.py
runstats/_core.cpython-36m-x86_64-linux-gnu.so
runstats-2.0.0.dist-info/RECORD
runstats-2.0.0.dist-info/METADATA
runstats-2.0.0.dist-info/top_level.txt
runstats-2.0.0.dist-info/WHEEL
runstats-2.0.0.dist-info/LICENSE
