Metadata-Version: 2.1
Name: runstats
Version: 2.0.0
Summary: Compute statistics and regression in one pass
Home-page: http://www.grantjenks.com/docs/runstats/
Author: Grant Jenks
Author-email: contact@grantjenks.com
License: Apache 2.0
Project-URL: Documentation, http://www.grantjenks.com/docs/runstats/
Project-URL: Funding, http://gum.co/runstats
Project-URL: Source, https://github.com/grantjenks/python-runstats
Project-URL: Tracker, https://github.com/grantjenks/python-runstats/issues
Platform: UNKNOWN
Classifier: Development Status :: 5 - Production/Stable
Classifier: Intended Audience :: Developers
Classifier: License :: OSI Approved :: Apache Software License
Classifier: Natural Language :: English
Classifier: Programming Language :: Python
Classifier: Programming Language :: Python :: 3
Classifier: Programming Language :: Python :: 3.6
Classifier: Programming Language :: Python :: 3.7
Classifier: Programming Language :: Python :: 3.8
Classifier: Programming Language :: Python :: 3.9
Classifier: Programming Language :: Python :: Implementation :: CPython
Requires-Python: >=3.6
